odoo/addons/l10n_mx_catalogs/README.rst
odoo/addons/l10n_mx_catalogs/__init__.py
odoo/addons/l10n_mx_catalogs/__manifest__.py
odoo/addons/l10n_mx_catalogs/import_catalogs_xls.py
odoo/addons/l10n_mx_catalogs/data/l10n_mx_catalogs.c_clave_prod_serv.csv
odoo/addons/l10n_mx_catalogs/data/l10n_mx_catalogs.c_clave_unidad.csv
odoo/addons/l10n_mx_catalogs/data/l10n_mx_catalogs.c_codigo_postal.csv
odoo/addons/l10n_mx_catalogs/data/l10n_mx_catalogs.c_colonia.csv
odoo/addons/l10n_mx_catalogs/data/l10n_mx_catalogs.c_config_autotransporte.csv
odoo/addons/l10n_mx_catalogs/data/l10n_mx_catalogs.c_figura_transporte.csv
odoo/addons/l10n_mx_catalogs/data/l10n_mx_catalogs.c_forma_pago.csv
odoo/addons/l10n_mx_catalogs/data/l10n_mx_catalogs.c_localidad.csv
odoo/addons/l10n_mx_catalogs/data/l10n_mx_catalogs.c_meses.csv
odoo/addons/l10n_mx_catalogs/data/l10n_mx_catalogs.c_metodo_pago.csv
odoo/addons/l10n_mx_catalogs/data/l10n_mx_catalogs.c_motivo_cancelacion.csv
odoo/addons/l10n_mx_catalogs/data/l10n_mx_catalogs.c_pais.csv
odoo/addons/l10n_mx_catalogs/data/l10n_mx_catalogs.c_parte_transporte.csv
odoo/addons/l10n_mx_catalogs/data/l10n_mx_catalogs.c_periodicidad.csv
odoo/addons/l10n_mx_catalogs/data/l10n_mx_catalogs.c_regimen_fiscal.csv
odoo/addons/l10n_mx_catalogs/data/l10n_mx_catalogs.c_sub_tipo_rem.csv
odoo/addons/l10n_mx_catalogs/data/l10n_mx_catalogs.c_tipo_permiso.csv
odoo/addons/l10n_mx_catalogs/data/l10n_mx_catalogs.c_tipo_relacion.csv
odoo/addons/l10n_mx_catalogs/data/l10n_mx_catalogs.c_uso_cfdi.csv
odoo/addons/l10n_mx_catalogs/i18n/l10n_mx_catalogs.pot
odoo/addons/l10n_mx_catalogs/models/__init__.py
odoo/addons/l10n_mx_catalogs/models/clave_prod_serv.py
odoo/addons/l10n_mx_catalogs/models/clave_unidad.py
odoo/addons/l10n_mx_catalogs/models/codigo_postal.py
odoo/addons/l10n_mx_catalogs/models/colonia.py
odoo/addons/l10n_mx_catalogs/models/config_autotransporte.py
odoo/addons/l10n_mx_catalogs/models/figura_transporte.py
odoo/addons/l10n_mx_catalogs/models/forma_pago.py
odoo_addon_l10n_mx_catalogs-17.0.1.2.0.dist-info/METADATA
odoo_addon_l10n_mx_catalogs-17.0.1.2.0.dist-info/WHEEL
odoo_addon_l10n_mx_catalogs-17.0.1.2.0.dist-info/top_level.txt
odoo_addon_l10n_mx_catalogs-17.0.1.2.0.dist-info/RECORD
